pylint_boolean_naming/__init__.py
pylint_boolean_naming/checker.py
pylint_boolean_naming-0.2.0.dist-info/LICENSE
pylint_boolean_naming-0.2.0.dist-info/METADATA
pylint_boolean_naming-0.2.0.dist-info/WHEEL
pylint_boolean_naming-0.2.0.dist-info/RECORD
