Metadata-Version: 2.1
Name: pylint-boolean-naming
Version: 0.2.0
Summary: Pylint Plugin for enforcing boolean variable naming
License: GNU GPLv3
Author: Ryan Ozawa
Author-email: ryan.ozawa21@gmail.com
Requires-Python: >=3.8,<4.0
Classifier: License :: Other/Proprietary License
Classifier: Programming Language :: Python :: 3
Classifier: Programming Language :: Python :: 3.8
Classifier: Programming Language :: Python :: 3.9
Classifier: Programming Language :: Python :: 3.10
Classifier: Programming Language :: Python :: 3.11
Classifier: Programming Language :: Python :: 3.12
Requires-Dist: astroid (>=3.0.3,<4.0.0)
Requires-Dist: pylint (>=3.0.3,<4.0.0)
